pidibble/__init__.py
pidibble/baseparsers.py
pidibble/baserecord.py
pidibble/hex.py
pidibble/mmcif_parse.py
pidibble/pdbparse.py
pidibble/pdbrecord.py
pidibble/resources/__init__.py
pidibble/resources/mmcif_format.yaml
pidibble/resources/pdb_format.yaml
pidibble-1.5.2.dist-info/METADATA
pidibble-1.5.2.dist-info/WHEEL
pidibble-1.5.2.dist-info/licenses/LICENSE
pidibble-1.5.2.dist-info/RECORD
