Metadata-Version: 2.4
Name: pidibble
Version: 1.5.2
Summary: A complete Protein Data Bank (PDB) file parser
Project-URL: Source, https://github.com/cameronabrams/pidibble
Project-URL: Documentation, https://pidibble.readthedocs.io/en/latest/
Project-URL: Bug Tracker, https://github.com/cameronabrams/pidibble/issues
Author-email: Cameron F Abrams <cfa22@drexel.edu>
License-File: LICENSE
Classifier: License :: OSI Approved :: MIT License
Classifier: Operating System :: OS Independent
Classifier: Programming Language :: Python :: 3
Requires-Python: >=3.7
Requires-Dist: mmcif
Requires-Dist: numpy>=1.24
Requires-Dist: pyyaml>=6
